configalchemy/__init__.py
configalchemy/configalchemy.py
configalchemy/field.py
configalchemy/lazy.py
configalchemy/meta.py
configalchemy/types.py
configalchemy/utils.py
configalchemy/contrib/__init__.py
configalchemy/contrib/apollo.py
configalchemy-0.5.5.dist-info/AUTHORS.rst
configalchemy-0.5.5.dist-info/LICENSE
configalchemy-0.5.5.dist-info/METADATA
configalchemy-0.5.5.dist-info/WHEEL
configalchemy-0.5.5.dist-info/top_level.txt
configalchemy-0.5.5.dist-info/RECORD
