Metadata-Version: 2.1
Name: configalchemy
Version: 0.5.5
Summary: The Settings and Configuration on ideal practices for app development.
Home-page: https://github.com/GuangTianLi/configalchemy
Author: GuangTian Li
Author-email: guangtian_li@qq.com
License: UNKNOWN
Keywords: configalchemy
Platform: UNKNOWN
Classifier: Development Status :: 2 - Pre-Alpha
Classifier: Intended Audience :: Developers
Classifier: Natural Language :: English
Classifier: Programming Language :: Python :: 3
Classifier: Programming Language :: Python :: 3.6
Classifier: Programming Language :: Python :: 3.7
Classifier: Programming Language :: Python :: 3.8
Classifier: Programming Language :: Python :: 3.9
Requires-Python: >=3.6.0
Requires-Dist: contextvars ; python_version < "3.7"
Provides-Extra: apollo
Requires-Dist: requests ; extra == 'apollo'
Provides-Extra: tests
Requires-Dist: requests ; extra == 'tests'
